cradl/__init__.py
cradl/backoff.py
cradl/client.py
cradl/content.py
cradl/credentials.py
cradl/log.py
cradl/response.py
cradl-0.4.9.dist-info/licenses/LICENSE.md
cradl-0.4.9.dist-info/METADATA
cradl-0.4.9.dist-info/WHEEL
cradl-0.4.9.dist-info/top_level.txt
cradl-0.4.9.dist-info/RECORD
