Metadata-Version: 2.4
Name: cradl
Version: 0.4.9
Summary: Python SDK for Cradl
Author-email: Cradl <hello@cradl.ai>
License: Apache 2.0
Project-URL: Homepage, https://github.com/CradlAI/cradl-sdk-python
Requires-Python: >=3.10
License-File: LICENSE.md
Requires-Dist: filetype>=1.2.0
Requires-Dist: requests>=2.31.0
Provides-Extra: dev
Requires-Dist: flake8>=5.0.4; extra == "dev"
Requires-Dist: mypy>=1.14.1; extra == "dev"
Requires-Dist: pytest>=8.3.5; extra == "dev"
Requires-Dist: pytest-env>=1.1.5; extra == "dev"
Requires-Dist: requests-mock>=1.12.1; extra == "dev"
Requires-Dist: tox>=4.25.0; extra == "dev"
Dynamic: license-file
